sqltrack/__init__.py
sqltrack/__main__.py
sqltrack/args.py
sqltrack/client.py
sqltrack/model.py
sqltrack/notebook.py
sqltrack/pandas.py
sqltrack/queries.py
sqltrack/sigterm.py
sqltrack/util.py
sqltrack/commands/__init__.py
sqltrack/commands/setup.py
sqltrack/css/notebook.css
sqltrack/sql/base.sql
sqltrack-0.1.4.dist-info/LICENSE
sqltrack-0.1.4.dist-info/METADATA
sqltrack-0.1.4.dist-info/WHEEL
sqltrack-0.1.4.dist-info/entry_points.txt
sqltrack-0.1.4.dist-info/top_level.txt
sqltrack-0.1.4.dist-info/RECORD
