Metadata-Version: 2.1
Name: sqltrack
Version: 0.1.4
Summary: SQL-based experiment tracking
Author-email: Joachim Folz <joachim.folz@dfki.de>
Maintainer-email: Joachim Folz <joachim.folz@dfki.de>
License: MIT License
Project-URL: Homepage, https://gitlab.com/jfolz/sqltrack
Project-URL: Documentation, https://gitlab.com/jfolz/sqltrack/-/blob/main/README.md
Project-URL: Source, https://gitlab.com/jfolz/sqltrack
Project-URL: Bug Reports, https://gitlab.com/jfolz/sqltrack/-/issues
Project-URL: Changelog, https://gitlab.com/jfolz/sqltrack/-/blob/main/CHANGELOG
Project-URL: License, https://gitlab.com/jfolz/sqltrack/-/blob/main/LICENSE
Keywords: SQL,postgres,PostgreSQL,machine learning,ML,experiment tracking,experiment,tracking,jupyter,jupyterlab,notebook
Classifier: Development Status :: 3 - Alpha
Classifier: Intended Audience :: Developers
Classifier: Intended Audience :: Science/Research
Classifier: Topic :: Software Development :: Build Tools
Classifier: License :: OSI Approved :: MIT License
Classifier: Programming Language :: SQL
Classifier: Topic :: Scientific/Engineering
Classifier: Topic :: Scientific/Engineering :: Visualization
Requires-Python: >=3.7
License-File: LICENSE
Requires-Dist: docopt-ng (<1.0.0,>=0.8.1)
Requires-Dist: psycopg[binary] (<4.0.0,>=3.1.8)
Provides-Extra: docs
Requires-Dist: sphinx (<7.0.0,>=6.1.3) ; extra == 'docs'
Requires-Dist: sphinxcontrib-programoutput (<1.0.0,>=0.17) ; extra == 'docs'
Requires-Dist: nbsphinx (<1.0.0,>=0.9.0) ; extra == 'docs'
Requires-Dist: furo ; extra == 'docs'
Provides-Extra: full
Requires-Dist: humanize (<5.0.0,>=4.6.0) ; extra == 'full'
Requires-Dist: ipython (<9.0.0,>=8.8.0) ; extra == 'full'
Requires-Dist: ipywidgets (<9.0.0,>=8.0.4) ; extra == 'full'
Requires-Dist: itables (<2.0.0,>=1.4.5) ; extra == 'full'
Requires-Dist: pandas (<2.0.0,>=1.5.3) ; extra == 'full'
Requires-Dist: plotly (<6.0.0,>=5.13.0) ; extra == 'full'
